bert_text_summarizer/__init__.py
bert_text_summarizer/cli/__init__.py
bert_text_summarizer/cli/main.py
bert_text_summarizer/extractive/__init__.py
bert_text_summarizer/extractive/article_chunk.py
bert_text_summarizer/extractive/decode_tf_record.py
bert_text_summarizer/extractive/input_features.py
bert_text_summarizer/extractive/input_preprocessing.py
bert_text_summarizer/extractive/model.py
bert_text_summarizer/extractive/cnndm/__init__.py
bert_text_summarizer/extractive/cnndm/data_loader.py
bert_text_summarizer/metrics/__init__.py
bert_text_summarizer/metrics/rouge.py
test/__init__.py
test/metrics/__init__.py
test/metrics/test_rouge.py
bert_text_summarizer-0.0.2.dist-info/METADATA
bert_text_summarizer-0.0.2.dist-info/WHEEL
bert_text_summarizer-0.0.2.dist-info/entry_points.txt
bert_text_summarizer-0.0.2.dist-info/top_level.txt
bert_text_summarizer-0.0.2.dist-info/RECORD
